stepview/__init__.py
stepview/data.py
stepview/entrypoint.py
stepview/tui.py
stepview-0.4.2.dist-info/entry_points.txt
stepview-0.4.2.dist-info/LICENSE
stepview-0.4.2.dist-info/WHEEL
stepview-0.4.2.dist-info/METADATA
stepview-0.4.2.dist-info/RECORD
