Metadata-Version: 2.1
Name: stepview
Version: 0.4.2
Summary: 1 global view of all your stepfunctions statemachines
License: GNU GPLv3
Author: vincent
Author-email: vclaes1986@gmail.com
Requires-Python: >=3.7,<4.0
Classifier: License :: Other/Proprietary License
Classifier: Programming Language :: Python :: 3
Classifier: Programming Language :: Python :: 3.10
Classifier: Programming Language :: Python :: 3.7
Classifier: Programming Language :: Python :: 3.8
Classifier: Programming Language :: Python :: 3.9
Requires-Dist: boto3 (>=1.21.42,<2.0.0)
Requires-Dist: pendulum (>=2.1.2,<3.0.0)
Requires-Dist: rich (>=12.0.1,<13.0.0)
Requires-Dist: textual (>=0.1.17,<0.2.0)
Requires-Dist: typer (>=0.4.1,<0.5.0)
